necta_fetcher/__init__.py
necta_fetcher/client.py
necta_fetcher/exceptions.py
necta_fetcher-0.5.0.dist-info/METADATA
necta_fetcher-0.5.0.dist-info/WHEEL
necta_fetcher-0.5.0.dist-info/top_level.txt
necta_fetcher-0.5.0.dist-info/RECORD
