Metadata-Version: 2.4
Name: necta-fetcher
Version: 0.5.0
Summary: A Python client to fetch NECTA (National Examinations Council of Tanzania) results with names.
Home-page: https://boyoftime.github.io/necta-fetcher
Author: Someless
Author-email: adosomeless@gmail.com
License: MIT
Project-URL: Bug Tracker, https://boyoftime.github.io/necta-fetcher
Keywords: necta results tanzania education examination fetcher scraper api client
Classifier: Development Status :: 3 - Alpha
Classifier: Intended Audience :: Developers
Classifier: Topic :: Software Development :: Libraries :: Python Modules
Classifier: Topic :: Education
Classifier: License :: OSI Approved :: MIT License
Classifier: Programming Language :: Python :: 3
Classifier: Programming Language :: Python :: 3.7
Classifier: Programming Language :: Python :: 3.8
Classifier: Programming Language :: Python :: 3.9
Classifier: Programming Language :: Python :: 3.10
Classifier: Programming Language :: Python :: 3.11
Classifier: Operating System :: OS Independent
Requires-Python: >=3.7
Requires-Dist: requests>=2.20.0
Requires-Dist: beautifulsoup4>=4.9.0
Dynamic: author
Dynamic: author-email
Dynamic: classifier
Dynamic: description
Dynamic: description-content-type
Dynamic: home-page
Dynamic: keywords
Dynamic: license
Dynamic: project-url
Dynamic: requires-dist
Dynamic: requires-python
Dynamic: summary
